{"cameraMode":{"drawMode":0,"name":"Shaded","section":"Shading Mode"},"sceneLighting":true,"audioPlay":false,"sceneViewState":{"m_AlwaysRefresh":false,"showFog":true,"showSkybox":true,"showFlares":true,"showImageEffects":true,"showParticleSystems":true,"showVisualEffectGraphs":true,"m_FxEnabled":true},"in2DMode":false,"pivot":{"x":-9.44489574432373,"y":-8.050946235656739,"z":8.662195205688477},"rotation":{"x":-0.1578742414712906,"y":0.08421812206506729,"z":-0.01361220981925726,"w":-0.9839507937431336},"size":37.89035415649414,"orthographic":false}